{
  "configVersion": 1,
  "timestamp": 1553013422552,
  "index": "/cv/index.html",
  "assetGroups": [
    {
      "name": "app",
      "installMode": "prefetch",
      "updateMode": "prefetch",
      "urls": [
        "/cv/index.html",
        "/cv/main.171a302667f1021647e5.js",
        "/cv/polyfills.fb7fa3593a34bf9b8824.js",
        "/cv/runtime.a5dd35324ddfd942bef1.js",
        "/cv/styles.256c2eecc1c927ac63be.css"
      ],
      "patterns": []
    },
    {
      "name": "assets",
      "installMode": "lazy",
      "updateMode": "prefetch",
      "urls": [
        "/cv/assets/print.css",
        "/cv/data/events.json",
        "/cv/data/profile.json"
      ],
      "patterns": []
    }
  ],
  "dataGroups": [],
  "hashTable": {
    "/cv/assets/print.css": "172f4708ac981ff7b854274ea49eb10021f4611c",
    "/cv/data/events.json": "b25c5dab63074ce9c347de01132a9b9815fbfcc0",
    "/cv/data/profile.json": "21747d47ceac2ab72c5c73154ffbedd87e3d6dcb",
    "/cv/index.html": "6b76faaa47b7c2f00f4127ecccca6f357bcf56c4",
    "/cv/main.171a302667f1021647e5.js": "3e0c15da2cdedd8df12ac0f28b815582d75ca0ff",
    "/cv/polyfills.fb7fa3593a34bf9b8824.js": "4f7d0f63b906aa376eb9c7bc6f0abfae545593a0",
    "/cv/runtime.a5dd35324ddfd942bef1.js": "b62956c2192bfe5516d6374e753773901ed50ec5",
    "/cv/styles.256c2eecc1c927ac63be.css": "abb1bddc1e5cc649f987ea7e21d006db296a876a"
  },
  "navigationUrls": [
    {
      "positive": true,
      "regex": "^\\/.*$"
    },
    {
      "positive": false,
      "regex": "^\\/(?:.+\\/)?[^/]*\\.[^/]*$"
    },
    {
      "positive": false,
      "regex": "^\\/(?:.+\\/)?[^/]*__[^/]*$"
    },
    {
      "positive": false,
      "regex": "^\\/(?:.+\\/)?[^/]*__[^/]*\\/.*$"
    }
  ]
}